pyfragments/__init__.py
pyfragments/svg.py
pyfragments/tests/test_svg.py
pyfragments/tests/test_warning.py
pyfragments-0.4.1.dist-info/LICENSE
pyfragments-0.4.1.dist-info/METADATA
pyfragments-0.4.1.dist-info/WHEEL
pyfragments-0.4.1.dist-info/top_level.txt
pyfragments-0.4.1.dist-info/RECORD
