Metadata-Version: 2.1
Name: pyfragments
Version: 0.4.1
Summary: Add animations to revealjs presentations from Python code-blocks.
Author-email: Mauro Silberberg <maurosilber@gmail.com>
License: MIT License
Project-URL: Homepage, https://github.com/maurosilber/pyfragments
Project-URL: Bug Tracker, https://github.com/maurosilber/pyfragments/issues
Keywords: quarto,revealjs,presentation,fragments,animations,matplotlib
Classifier: Programming Language :: Python :: 3
Classifier: License :: OSI Approved :: MIT License
Classifier: Operating System :: OS Independent
Classifier: Intended Audience :: Developers
Classifier: Intended Audience :: Science/Research
Classifier: Topic :: Scientific/Engineering
Classifier: Topic :: Software Development :: Libraries
Requires-Python: >=3.9
License-File: LICENSE
Requires-Dist: imageio
Requires-Dist: IPython
Requires-Dist: matplotlib
Provides-Extra: test
Requires-Dist: numpy ; extra == 'test'
Requires-Dist: pytest ; extra == 'test'
